sharepoint_crud/__init__.py
sharepoint_crud/sharepoint.py
sharepoint_crud-2.0.dist-info/LICENSE
sharepoint_crud-2.0.dist-info/METADATA
sharepoint_crud-2.0.dist-info/WHEEL
sharepoint_crud-2.0.dist-info/top_level.txt
sharepoint_crud-2.0.dist-info/RECORD
