Metadata-Version: 2.1
Name: sharepoint-crud
Version: 2.0
Summary: Library for interacting with SharePoint
Home-page: https://github.com/almemanuel/sharepoint-crud
Author: Emanuel Almeida
Author-email: emanuel.almeida1998@outlook.com
Keywords: sharepoint office365
Classifier: Programming Language :: Python :: 3
Classifier: License :: OSI Approved :: MIT License
Classifier: Operating System :: OS Independent
License-File: LICENSE
Requires-Dist: office365-rest-python-client (==2.2.0)
